odoo/addons/mrp_unbuild_valuation_layer_link/README.rst
odoo/addons/mrp_unbuild_valuation_layer_link/__init__.py
odoo/addons/mrp_unbuild_valuation_layer_link/__manifest__.py
odoo/addons/mrp_unbuild_valuation_layer_link/i18n/mrp_unbuild_valuation_layer_link.pot
odoo/addons/mrp_unbuild_valuation_layer_link/models/__init__.py
odoo/addons/mrp_unbuild_valuation_layer_link/models/mrp_unbuild.py
odoo/addons/mrp_unbuild_valuation_layer_link/readme/CONTRIBUTORS.rst
odoo/addons/mrp_unbuild_valuation_layer_link/readme/DESCRIPTION.rst
odoo/addons/mrp_unbuild_valuation_layer_link/readme/USAGE.rst
odoo/addons/mrp_unbuild_valuation_layer_link/static/description/icon.png
odoo/addons/mrp_unbuild_valuation_layer_link/static/description/index.html
odoo/addons/mrp_unbuild_valuation_layer_link/tests/__init__.py
odoo/addons/mrp_unbuild_valuation_layer_link/tests/test_mrp__unbuild_valuation_layer_link.py
odoo/addons/mrp_unbuild_valuation_layer_link/views/mrp_unbuild_views.xml
odoo14_addon_mrp_unbuild_valuation_layer_link-14.0.1.0.1.dist-info/METADATA
odoo14_addon_mrp_unbuild_valuation_layer_link-14.0.1.0.1.dist-info/WHEEL
odoo14_addon_mrp_unbuild_valuation_layer_link-14.0.1.0.1.dist-info/top_level.txt
odoo14_addon_mrp_unbuild_valuation_layer_link-14.0.1.0.1.dist-info/RECORD
